benchllm/__init__.py
benchllm/cache.py
benchllm/cli/__init__.py
benchllm/cli/commands/__init__.py
benchllm/cli/commands/add_test.py
benchllm/cli/commands/evaluate.py
benchllm/cli/commands/list_tests.py
benchllm/cli/commands/run_suite.py
benchllm/cli/evaluator/__init__.py
benchllm/cli/evaluator/interactive.py
benchllm/cli/evaluator/web.py
benchllm/cli/listener.py
benchllm/cli/main.py
benchllm/cli/utils.py
benchllm/data_types.py
benchllm/evaluator/__init__.py
benchllm/evaluator/embedding.py
benchllm/evaluator/evaluator.py
benchllm/evaluator/semantic.py
benchllm/evaluator/string_match.py
benchllm/input_types.py
benchllm/listener.py
benchllm/similarity.py
benchllm/singleton.py
benchllm/tester.py
benchllm/utils.py
benchllm-0.3.0.dist-info/LICENSE
benchllm-0.3.0.dist-info/WHEEL
benchllm-0.3.0.dist-info/METADATA
benchllm-0.3.0.dist-info/entry_points.txt
benchllm-0.3.0.dist-info/RECORD
