Metadata-Version: 2.1
Name: benchllm
Version: 0.3.0
Summary: Tool for testing LLMs
Home-page: https://github.com/v7labs/benchllm
License: MIT
Author: Simon Edwardsson
Author-email: simon@v7labs.com
Requires-Python: >=3.10,<3.12
Classifier: License :: OSI Approved :: MIT License
Classifier: Programming Language :: Python :: 3
Classifier: Programming Language :: Python :: 3.10
Classifier: Programming Language :: Python :: 3.11
Classifier: Programming Language :: Python :: 3
Provides-Extra: dev
Provides-Extra: examples
Provides-Extra: test
Requires-Dist: faiss-cpu ; extra == "examples"
Requires-Dist: langchain ; extra == "examples"
Requires-Dist: openai
Requires-Dist: pydantic (>=1.10.9,<2.0.0)
Requires-Dist: pypdf ; extra == "examples"
Requires-Dist: pytest ; extra == "dev" or extra == "test"
Requires-Dist: pywebio
Requires-Dist: pyyaml (>=5.1)
Requires-Dist: tiktoken ; extra == "examples"
Requires-Dist: typer[all]
Requires-Dist: types-pyyaml ; extra == "dev"
